LICENSE.txt
MANIFEST.in
README.rst
VERSION
setup.cfg
setup.py
mlphon/__init__.py
mlphon/cli.py
mlphon/g2p.py
mlphon/phonetic_analyser.py
mlphon/syllable_analyser.py
mlphon/utilities.py
mlphon.egg-info/PKG-INFO
mlphon.egg-info/SOURCES.txt
mlphon.egg-info/dependency_links.txt
mlphon.egg-info/entry_points.txt
mlphon.egg-info/not-zip-safe
mlphon.egg-info/requires.txt
mlphon.egg-info/top_level.txt
mlphon/data/analysis.a
mlphon/data/g2p.a
mlphon/data/ml2ipa.a
mlphon/data/syllablizer.a