Metadata-Version: 1.1
Name: mlphon
Version: 3.1.1
Summary: Malayalam phonetic analyser
Home-page: https://gitlab.com/smc/mlphon
Author: Kavya Manohar
Author-email: sakhi.kavya@gmail.com
License: MIT
Keywords: Malayalam phonetic FST analyser generator IPA syllable
Platform: UNKNOWN
Classifier: Programming Language :: Python :: 3
Classifier: Programming Language :: Python :: 3.5
Classifier: Programming Language :: Python :: 3.6
Classifier: License :: OSI Approved :: MIT License
Classifier: Intended Audience :: Developers
